classyconf/__init__.py
classyconf/casts.py
classyconf/configuration.py
classyconf/exceptions.py
classyconf/loaders.py
classyconf/parsers.py
classyconf-0.5.2.dist-info/LICENSE.txt
classyconf-0.5.2.dist-info/WHEEL
classyconf-0.5.2.dist-info/METADATA
classyconf-0.5.2.dist-info/RECORD
