Metadata-Version: 2.1
Name: classyconf
Version: 0.5.2
Summary: Extensible library for separation of settings from code.
Home-page: https://github.com/hernantz/classyconf
License: MIT
Author: Hernan Lozano
Author-email: hernantz@gmail.com
Requires-Python: >=3.7,<4.0
Classifier: Development Status :: 5 - Production/Stable
Classifier: Intended Audience :: Developers
Classifier: License :: OSI Approved :: MIT License
Classifier: Programming Language :: Python :: 3
Classifier: Programming Language :: Python :: 3.7
Classifier: Programming Language :: Python :: 3.8
Classifier: Programming Language :: Python :: 3.9
Classifier: Topic :: Software Development :: Build Tools
Classifier: Topic :: Software Development :: Libraries :: Python Modules
Classifier: Topic :: System :: Archiving :: Packaging
Classifier: Topic :: Utilities
Project-URL: Documentation, https://classyconf.readthedocs.io/en/latest/
Project-URL: Repository, https://github.com/hernantz/classyconf
